pyeasyencrypt/__init__.py
pyeasyencrypt/pyeasyencrypt.py
pyeasyencrypt-0.1.0.dist-info/LICENSE
pyeasyencrypt-0.1.0.dist-info/METADATA
pyeasyencrypt-0.1.0.dist-info/WHEEL
pyeasyencrypt-0.1.0.dist-info/top_level.txt
pyeasyencrypt-0.1.0.dist-info/RECORD
