Metadata-Version: 2.1
Name: pyeasyencrypt
Version: 0.1.0
Summary: Your easy tool to encrypt and decrypt strings with a password
Author-email: Jordi Redondo <jordipromotions@gmail.com>
Project-URL: Homepage, https://github.com/user/pyeasyencrypt
Project-URL: Bug Tracker, https://github.com/user/pyeasyencrypt/issues
Classifier: Programming Language :: Python :: 3
Classifier: License :: OSI Approved :: MIT License
Classifier: Operating System :: OS Independent
Requires-Python: >=3.7
License-File: LICENSE
Requires-Dist: cryptography
